pd1/mem.v

module mem #(parameter MEM_DEPTH = 250000)(
    w_data_in_32,
    w_data_out_32,
    w_addr_32,
    rw,
    en,
    clock    
);

reg[7:0] memory_block[MEM_DEPTH : 0];

input wire[31:0] w_data_in_32;
input wire[31:0] w_addr_32;

input clock, rw, en;

output wire[31:0] w_data_out_32;

assign w_data_out_32 = {memory_block[w_addr_32], memory_block[w_addr_32 + 1], memory_block[w_addr_32 + 2], memory_block[w_addr_32 + 3]};

always @(posedge clock) begin
    if(en)
    begin
        if(~rw)
        begin
            memory_block[w_addr_32 + 3] <= w_data_in_32[7:0];
            memory_block[w_addr_32 + 2] <= w_data_in_32[15:8];
            memory_block[w_addr_32 + 1] <= w_data_in_32[23:16];
            memory_block[w_addr_32] <= w_data_in_32[31:24];
        end
    end
end
endmodule

pd1/mem_test.v
`include "mem.v"
module mem_test #(parameter LOCAL_MEM_SIZE = 27);
    reg [31:0] addr, data_in;
    wire [31:0] data_out;
    reg rw, enable, read_back;
    reg clock = 1;

    reg [31:0] local_mem [1000 : 0];
    
    integer counter = 0;
    initial begin
        $dumpfile("mem_test.vcd");
        $dumpvars(0, clock);
        $dumpvars(0, addr);
        $dumpvars(0, data_in);
        $dumpvars(0, data_out);
        $dumpvars(0, rw);
        $dumpvars(0, enable);
        $dumpvars(0, counter);
        $dumpvars(0, read_back);

     /* 
        Basic functionality test
        #5 enable = 1;
        #15 addr = 32'h0; data_in = 32'hABCDABCD; rw = 0;
        #20 addr = 32'h04; data_in = 32'hDEFADEFA; rw = 0;
        #25 addr = 32'h08; data_in = 32'h12341234; rw = 0;
        #30 rw = 1;
        #35 addr = 32'h0;
        #40 addr = 32'h04;
        #45 addr = 32'h08;*/

        //large scale binary loading test
        enable = 1;
        rw = 0;   
        read_back = 0;     
        addr = 32'h0;
        $readmemh("mips-benchmarks/add.x", local_mem);
        #1000  $finish;
    end

    mem mem_block(.w_data_in_32(data_in),
    .w_data_out_32(data_out),
    .w_addr_32(addr),
    .rw(rw),
    .en(enable),
    .clock(clock));

    always @(posedge clock) begin
        if(~(local_mem[counter] === 32'bx)) 
        begin
        $display("Value: %h", local_mem[counter]);
            addr = addr + 4;
            data_in = local_mem[counter];
            counter = counter + 1;
        end
        else
        begin
            rw = 1;
            read_back = 1;
            addr = 32'h0;
        end
    end
        
    always @(posedge clock)begin
        if(read_back)
        begin
            addr = addr + 4;
        end
    end

    always begin
        #2 clock = ~clock;
    end

    always @(posedge clock) begin
        //$display("Addr:%h, Data_in:%h, Data_out:%h", addr, data_in, data_out);
    end
endmodule

pd1/mem_test.vcd
$date
	Tue May 15 23:53:25 2018
$end
$version
	Icarus Verilog
$end
$timescale
	1s
$end
$scope module mem_test $end
$var reg 1 ! clock $end
$upscope $end
$scope module mem_test $end
$var reg 32 " addr [31:0] $end
$upscope $end
$scope module mem_test $end
$var reg 32 # data_in [31:0] $end
$upscope $end
$scope module mem_test $end
$var wire 32 $ data_out [31:0] $end
$upscope $end
$scope module mem_test $end
$var reg 1 % rw $end
$upscope $end
$scope module mem_test $end
$var reg 1 & enable $end
$upscope $end
$scope module mem_test $end
$var integer 32 ' counter [31:0] $end
$upscope $end
$scope module mem_test $end
$var reg 1 ( read_back $end
$upscope $end
$enddefinitions $end
#0
$dumpvars
0(
b0 '
1&
0%
bx $
bx #
b0 "
1!
$end
#2
0!
#4
b1 '
b100111101111011111111111101000 #
b100 "
1!
#6
0!
#8
b100100000000100000000000000011 $
b10 '
b100100000000100000000000000011 #
b1000 "
1!
#10
0!
#12
b11 '
b10101111101000100000000000001000 #
bx $
b1100 "
1!
#14
0!
#16
b100100000000100000000000000010 $
b100 '
b100100000000100000000000000010 #
b10000 "
1!
#18
0!
#20
b101 '
b10101111101000100000000000001100 #
bx $
b10100 "
1!
#22
0!
#24
b10101111101000000000000000010000 $
b110 '
b10101111101000000000000000010000 #
b11000 "
1!
#26
0!
#28
b111 '
b10001111101000110000000000001000 #
bx $
b11100 "
1!
#30
0!
#32
b10001111101000100000000000001100 $
b1000 '
b10001111101000100000000000001100 #
b100000 "
1!
#34
0!
#36
b1001 '
b11000100001000000100001 #
bx $
b100100 "
1!
#38
0!
#40
b10101111101000100000000000010000 $
b1010 '
b10101111101000100000000000010000 #
b101000 "
1!
#42
0!
#44
b1011 '
b10001111101000100000000000010000 #
bx $
b101100 "
1!
#46
0!
#48
b100111101111010000000000011000 $
b1100 '
b100111101111010000000000011000 #
b110000 "
1!
#50
0!
#52
b1101 '
b11111000000000000000001000 #
bx $
b110100 "
1!
#54
0!
#56
b0 $
b1110 '
b0 #
b111000 "
1!
#58
0!
#60
b1111 '
bx $
b111100 "
1!
#62
0!
#64
b0 $
b10000 '
b1000000 "
1!
#66
0!
#68
b10001 '
b10100000000000000000000000001100 #
bx $
b1000100 "
1!
#70
0!
#72
b0 $
b10010 '
b0 #
b1001000 "
1!
#74
0!
#76
b10011 '
bx $
b1001100 "
1!
#78
0!
#80
b0 $
b10100 '
b1010000 "
1!
#82
0!
#84
b10101 '
bx $
b1010100 "
1!
#86
0!
#88
b0 $
b10110 '
b1011000 "
1!
#90
0!
#92
b10111 '
b10000000000001 #
bx $
b1011100 "
1!
#94
0!
#96
b1000000010000000000000001 $
b11000 '
b1000000010000000000000001 #
b1100000 "
1!
#98
0!
#100
b11001 '
b0 #
bx $
b1100100 "
1!
#102
0!
#104
b0 $
b11010 '
b1101000 "
1!
#106
0!
#108
b11011 '
b1 #
bx $
b1101100 "
1!
#110
0!
#112
b0 $
b11100 '
b0 #
b1110000 "
1!
#114
0!
#116
bx $
b0 "
1(
1%
1!
#118
0!
#120
b100 "
1!
#122
0!
#124
bx $
b0 "
1!
#126
0!
#128
b100 "
1!
#130
0!
#132
bx $
b0 "
1!
#134
0!
#136
b100 "
1!
#138
0!
#140
bx $
b0 "
1!
#142
0!
#144
b100 "
1!
#146
0!
#148
bx $
b0 "
1!
#150
0!
#152
b100 "
1!
#154
0!
#156
bx $
b0 "
1!
#158
0!
#160
b100 "
1!
#162
0!
#164
bx $
b0 "
1!
#166
0!
#168
b100 "
1!
#170
0!
#172
bx $
b0 "
1!
#174
0!
#176
b100 "
1!
#178
0!
#180
bx $
b0 "
1!
#182
0!
#184
b100 "
1!
#186
0!
#188
bx $
b0 "
1!
#190
0!
#192
b100 "
1!
#194
0!
#196
bx $
b0 "
1!
#198
0!
#200
b100 "
1!
#202
0!
#204
bx $
b0 "
1!
#206
0!
#208
b100 "
1!
#210
0!
#212
bx $
b0 "
1!
#214
0!
#216
b100 "
1!
#218
0!
#220
bx $
b0 "
1!
#222
0!
#224
b100 "
1!
#226
0!
#228
bx $
b0 "
1!
#230
0!
#232
b100 "
1!
#234
0!
#236
bx $
b0 "
1!
#238
0!
#240
b100 "
1!
#242
0!
#244
bx $
b0 "
1!
#246
0!
#248
b100 "
1!
#250
0!
#252
bx $
b0 "
1!
#254
0!
#256
b100 "
1!
#258
0!
#260
bx $
b0 "
1!
#262
0!
#264
b100 "
1!
#266
0!
#268
bx $
b0 "
1!
#270
0!
#272
b100 "
1!
#274
0!
#276
bx $
b0 "
1!
#278
0!
#280
b100 "
1!
#282
0!
#284
bx $
b0 "
1!
#286
0!
#288
b100 "
1!
#290
0!
#292
bx $
b0 "
1!
#294
0!
#296
b100 "
1!
#298
0!
#300
bx $
b0 "
1!
#302
0!
#304
b100 "
1!
#306
0!
#308
bx $
b0 "
1!
#310
0!
#312
b100 "
1!
#314
0!
#316
bx $
b0 "
1!
#318
0!
#320
b100 "
1!
#322
0!
#324
bx $
b0 "
1!
#326
0!
#328
b100 "
1!
#330
0!
#332
bx $
b0 "
1!
#334
0!
#336
b100 "
1!
#338
0!
#340
bx $
b0 "
1!
#342
0!
#344
b100 "
1!
#346
0!
#348
bx $
b0 "
1!
#350
0!
#352
b100 "
1!
#354
0!
#356
bx $
b0 "
1!
#358
0!
#360
b100 "
1!
#362
0!
#364
bx $
b0 "
1!
#366
0!
#368
b100 "
1!
#370
0!
#372
bx $
b0 "
1!
#374
0!
#376
b100 "
1!
#378
0!
#380
bx $
b0 "
1!
#382
0!
#384
b100 "
1!
#386
0!
#388
bx $
b0 "
1!
#390
0!
#392
b100 "
1!
#394
0!
#396
bx $
b0 "
1!
#398
0!
#400
b100 "
1!
#402
0!
#404
bx $
b0 "
1!
#406
0!
#408
b100 "
1!
#410
0!
#412
bx $
b0 "
1!
#414
0!
#416
b100 "
1!
#418
0!
#420
bx $
b0 "
1!
#422
0!
#424
b100 "
1!
#426
0!
#428
bx $
b0 "
1!
#430
0!
#432
b100 "
1!
#434
0!
#436
bx $
b0 "
1!
#438
0!
#440
b100 "
1!
#442
0!
#444
bx $
b0 "
1!
#446
0!
#448
b100 "
1!
#450
0!
#452
bx $
b0 "
1!
#454
0!
#456
b100 "
1!
#458
0!
#460
bx $
b0 "
1!
#462
0!
#464
b100 "
1!
#466
0!
#468
bx $
b0 "
1!
#470
0!
#472
b100 "
1!
#474
0!
#476
bx $
b0 "
1!
#478
0!
#480
b100 "
1!
#482
0!
#484
bx $
b0 "
1!
#486
0!
#488
b100 "
1!
#490
0!
#492
bx $
b0 "
1!
#494
0!
#496
b100 "
1!
#498
0!
#500
bx $
b0 "
1!
#502
0!
#504
b100 "
1!
#506
0!
#508
bx $
b0 "
1!
#510
0!
#512
b100 "
1!
#514
0!
#516
bx $
b0 "
1!
#518
0!
#520
b100 "
1!
#522
0!
#524
bx $
b0 "
1!
#526
0!
#528
b100 "
1!
#530
0!
#532
bx $
b0 "
1!
#534
0!
#536
b100 "
1!
#538
0!
#540
bx $
b0 "
1!
#542
0!
#544
b100 "
1!
#546
0!
#548
bx $
b0 "
1!
#550
0!
#552
b100 "
1!
#554
0!
#556
bx $
b0 "
1!
#558
0!
#560
b100 "
1!
#562
0!
#564
bx $
b0 "
1!
#566
0!
#568
b100 "
1!
#570
0!
#572
bx $
b0 "
1!
#574
0!
#576
b100 "
1!
#578
0!
#580
bx $
b0 "
1!
#582
0!
#584
b100 "
1!
#586
0!
#588
bx $
b0 "
1!
#590
0!
#592
b100 "
1!
#594
0!
#596
bx $
b0 "
1!
#598
0!
#600
b100 "
1!
#602
0!
#604
bx $
b0 "
1!
#606
0!
#608
b100 "
1!
#610
0!
#612
bx $
b0 "
1!
#614
0!
#616
b100 "
1!
#618
0!
#620
bx $
b0 "
1!
#622
0!
#624
b100 "
1!
#626
0!
#628
bx $
b0 "
1!
#630
0!
#632
b100 "
1!
#634
0!
#636
bx $
b0 "
1!
#638
0!
#640
b100 "
1!
#642
0!
#644
bx $
b0 "
1!
#646
0!
#648
b100 "
1!
#650
0!
#652
bx $
b0 "
1!
#654
0!
#656
b100 "
1!
#658
0!
#660
bx $
b0 "
1!
#662
0!
#664
b100 "
1!
#666
0!
#668
bx $
b0 "
1!
#670
0!
#672
b100 "
1!
#674
0!
#676
bx $
b0 "
1!
#678
0!
#680
b100 "
1!
#682
0!
#684
bx $
b0 "
1!
#686
0!
#688
b100 "
1!
#690
0!
#692
bx $
b0 "
1!
#694
0!
#696
b100 "
1!
#698
0!
#700
bx $
b0 "
1!
#702
0!
#704
b100 "
1!
#706
0!
#708
bx $
b0 "
1!
#710
0!
#712
b100 "
1!
#714
0!
#716
bx $
b0 "
1!
#718
0!
#720
b100 "
1!
#722
0!
#724
bx $
b0 "
1!
#726
0!
#728
b100 "
1!
#730
0!
#732
bx $
b0 "
1!
#734
0!
#736
b100 "
1!
#738
0!
#740
bx $
b0 "
1!
#742
0!
#744
b100 "
1!
#746
0!
#748
bx $
b0 "
1!
#750
0!
#752
b100 "
1!
#754
0!
#756
bx $
b0 "
1!
#758
0!
#760
b100 "
1!
#762
0!
#764
bx $
b0 "
1!
#766
0!
#768
b100 "
1!
#770
0!
#772
bx $
b0 "
1!
#774
0!
#776
b100 "
1!
#778
0!
#780
bx $
b0 "
1!
#782
0!
#784
b100 "
1!
#786
0!
#788
bx $
b0 "
1!
#790
0!
#792
b100 "
1!
#794
0!
#796
bx $
b0 "
1!
#798
0!
#800
b100 "
1!
#802
0!
#804
bx $
b0 "
1!
#806
0!
#808
b100 "
1!
#810
0!
#812
bx $
b0 "
1!
#814
0!
#816
b100 "
1!
#818
0!
#820
bx $
b0 "
1!
#822
0!
#824
b100 "
1!
#826
0!
#828
bx $
b0 "
1!
#830
0!
#832
b100 "
1!
#834
0!
#836
bx $
b0 "
1!
#838
0!
#840
b100 "
1!
#842
0!
#844
bx $
b0 "
1!
#846
0!
#848
b100 "
1!
#850
0!
#852
bx $
b0 "
1!
#854
0!
#856
b100 "
1!
#858
0!
#860
bx $
b0 "
1!
#862
0!
#864
b100 "
1!
#866
0!
#868
bx $
b0 "
1!
#870
0!
#872
b100 "
1!
#874
0!
#876
bx $
b0 "
1!
#878
0!
#880
b100 "
1!
#882
0!
#884
bx $
b0 "
1!
#886
0!
#888
b100 "
1!
#890
0!
#892
bx $
b0 "
1!
#894
0!
#896
b100 "
1!
#898
0!
#900
bx $
b0 "
1!
#902
0!
#904
b100 "
1!
#906
0!
#908
bx $
b0 "
1!
#910
0!
#912
b100 "
1!
#914
0!
#916
bx $
b0 "
1!
#918
0!
#920
b100 "
1!
#922
0!
#924
bx $
b0 "
1!
#926
0!
#928
b100 "
1!
#930
0!
#932
bx $
b0 "
1!
#934
0!
#936
b100 "
1!
#938
0!
#940
bx $
b0 "
1!
#942
0!
#944
b100 "
1!
#946
0!
#948
bx $
b0 "
1!
#950
0!
#952
b100 "
1!
#954
0!
#956
bx $
b0 "
1!
#958
0!
#960
b100 "
1!
#962
0!
#964
bx $
b0 "
1!
#966
0!
#968
b100 "
1!
#970
0!
#972
bx $
b0 "
1!
#974
0!
#976
b100 "
1!
#978
0!
#980
bx $
b0 "
1!
#982
0!
#984
b100 "
1!
#986
0!
#988
bx $
b0 "
1!
#990
0!
#992
b100 "
1!
#994
0!
#996
bx $
b0 "
1!
#998
0!
#1000
b100 "
1!
