pd1/mem.v

module mem #(parameter MEM_DEPTH = 250000)(
    w_data_in_32,
    w_data_out_32,
    w_addr_32,
    rw,
    en,
    clock    
);

reg[7:0] memory_block[MEM_DEPTH : 0];

input wire[31:0] w_data_in_32;
input wire[31:0] w_addr_32;

input clock, rw, en;

output wire[31:0] w_data_out_32;

assign w_data_out_32 = {memory_block[w_addr_32], memory_block[w_addr_32 + 1], memory_block[w_addr_32 + 2], memory_block[w_addr_32 + 3]};

always @(posedge clock) begin
    if(en)
    begin
        if(~rw)
        begin
            memory_block[w_addr_32 + 3] <= w_data_in_32[7:0];
            memory_block[w_addr_32 + 2] <= w_data_in_32[15:8];
            memory_block[w_addr_32 + 1] <= w_data_in_32[23:16];
            memory_block[w_addr_32] <= w_data_in_32[31:24];
        end
    end
end
endmodule

pd1/mem_test.v
`include "mem.v"
module mem_test;
    reg [31:0] addr, data_in;
    wire [31:0] data_out;
    reg rw, enable;
    reg clock = 1;

    initial begin
        $dumpfile("mem_test.vcd");
        $dumpvars(0, clock);
        $dumpvars(0, addr);
        $dumpvars(0, data_in);
        $dumpvars(0, data_out);
        $dumpvars(0, rw);
        $dumpvars(0, enable);

        #5 enable = 1;
        #15 addr = 32'h0; data_in = 32'hABCDABCD; rw = 0;
        #20 addr = 32'h04; data_in = 32'hDEFADEFA; rw = 0;
        #25 addr = 32'h08; data_in = 32'h12341234; rw = 0;
        #30 rw = 1;
        #35 addr = 32'h0;
        #40 addr = 32'h04;
        #45 addr = 32'h08;
        #50 $finish;
    end

    mem mem_block(.w_data_in_32(data_in),
    .w_data_out_32(data_out),
    .w_addr_32(addr),
    .rw(rw),
    .en(enable),
    .clock(clock));



    always begin
        #2 clock = ~clock;
    end

    always @(posedge clock) begin
        $display("Addr:%h, Data_in:%h, Data_out:%h", addr, data_in, data_out);
    end
endmodule

pd1/mem_test.vcd
$date
	Tue May 15 16:11:08 2018
$end
$version
	Icarus Verilog
$end
$timescale
	1s
$end
$scope module mem_test $end
$var reg 1 ! clock $end
$upscope $end
$scope module mem_test $end
$var reg 32 " addr [31:0] $end
$upscope $end
$scope module mem_test $end
$var reg 32 # data_in [31:0] $end
$upscope $end
$scope module mem_test $end
$var wire 32 $ data_out [31:0] $end
$upscope $end
$scope module mem_test $end
$var reg 1 % rw $end
$upscope $end
$scope module mem_test $end
$var reg 1 & enable $end
$upscope $end
$enddefinitions $end
#0
$dumpvars
x&
x%
bx $
bx #
bx "
1!
$end
#2
0!
#4
1!
#5
1&
#6
0!
#8
1!
#10
0!
#12
1!
#14
0!
#16
1!
#18
0!
#20
b10101011110011011010101111001101 $
1!
0%
b10101011110011011010101111001101 #
b0 "
#22
0!
#24
1!
#26
0!
#28
1!
#30
0!
#32
1!
#34
0!
#36
1!
#38
0!
#40
1!
b11011110111110101101111011111010 #
b11011110111110101101111011111010 $
b100 "
#42
0!
#44
1!
#46
0!
#48
1!
#50
0!
#52
1!
#54
0!
#56
1!
#58
0!
#60
1!
#62
0!
#64
1!
#65
b10010001101000001001000110100 #
bx $
b1000 "
#66
0!
#68
b10010001101000001001000110100 $
1!
#70
0!
#72
1!
#74
0!
#76
1!
#78
0!
#80
1!
#82
0!
#84
1!
#86
0!
#88
1!
#90
0!
#92
1!
#94
0!
#95
1%
#96
1!
#98
0!
#100
1!
#102
0!
#104
1!
#106
0!
#108
1!
#110
0!
#112
1!
#114
0!
#116
1!
#118
0!
#120
1!
#122
0!
#124
1!
#126
0!
#128
1!
#130
0!
b10101011110011011010101111001101 $
b0 "
#132
1!
#134
0!
#136
1!
#138
0!
#140
1!
#142
0!
#144
1!
#146
0!
#148
1!
#150
0!
#152
1!
#154
0!
#156
1!
#158
0!
#160
1!
#162
0!
#164
1!
#166
0!
#168
1!
#170
0!
b11011110111110101101111011111010 $
b100 "
#172
1!
#174
0!
#176
1!
#178
0!
#180
1!
#182
0!
#184
1!
#186
0!
#188
1!
#190
0!
#192
1!
#194
0!
#196
1!
#198
0!
#200
1!
#202
0!
#204
1!
#206
0!
#208
1!
#210
0!
#212
1!
#214
0!
#215
b10010001101000001001000110100 $
b1000 "
