pd1/mem.v

module mem #(parameter MEM_DEPTH = 250000)(
    w_data_in_32,
    w_data_out_32,
    w_addr_32,
    rw,
    en,
    clock    
);

reg[7:0] memory_block[MEM_DEPTH : 0];

input wire[31:0] w_data_in_32;
input wire[31:0] w_addr_32;

input clock, rw, en;

output wire[31:0] w_data_out_32;

assign w_data_out_32 = {memory_block[w_addr_32], memory_block[w_addr_32 + 1], memory_block[w_addr_32 + 2], memory_block[w_addr_32 + 3]};

always @(posedge clock) begin
    if(en)
    begin
        if(~rw)
        begin
            memory_block[w_addr_32 + 3] <= w_data_in_32[7:0];
            memory_block[w_addr_32 + 2] <= w_data_in_32[15:8];
            memory_block[w_addr_32 + 1] <= w_data_in_32[23:16];
            memory_block[w_addr_32] <= w_data_in_32[31:24];
        end
    end
end
endmodule

pd1/mem_test.v
`include "mem.v"
module mem_test #(parameter LOCAL_MEM_SIZE = 27);
    reg [31:0] addr, data_in;
    wire [31:0] data_out;
    reg rw, enable, read_back;
    reg clock = 1;

    reg [31:0] local_mem [1000 : 0];
    
    integer counter = 0;
    initial begin
        $dumpfile("mem_test.vcd");
        $dumpvars(0, clock);
        $dumpvars(0, addr);
        $dumpvars(0, data_in);
        $dumpvars(0, data_out);
        $dumpvars(0, rw);
        $dumpvars(0, enable);
        $dumpvars(0, counter);
        $dumpvars(0, read_back);

     /* 
        Basic functionality test
        #5 enable = 1;
        #15 addr = 32'h0; data_in = 32'hABCDABCD; rw = 0;
        #20 addr = 32'h04; data_in = 32'hDEFADEFA; rw = 0;
        #25 addr = 32'h08; data_in = 32'h12341234; rw = 0;
        #30 rw = 1;
        #35 addr = 32'h0;
        #40 addr = 32'h04;
        #45 addr = 32'h08;*/

        //large scale binary loading test
        enable = 1;
        rw = 0;   
        read_back = 0;     
        addr = 32'h0;
        $readmemh("mips-benchmarks/add.x", local_mem);
        #1000  $finish;
    end

    mem mem_block(.w_data_in_32(data_in),
    .w_data_out_32(data_out),
    .w_addr_32(addr),
    .rw(rw),
    .en(enable),
    .clock(clock));

    always @(posedge clock) begin
        if(~(local_mem[counter] === 32'bx)) 
        begin
        $display("Value: %h", local_mem[counter]);
            addr = addr + 4;
            data_in = local_mem[counter];
            counter = counter + 1;
        end
        else
        begin
            rw = 1;
            read_back = 1;
            addr = 32'h0;
        end
    end
        
    always @(posedge clock)begin
        if(read_back)
        begin
            addr = addr + 4;
        end
    end

    always begin
        #2 clock = ~clock;
    end

    always @(posedge clock) begin
        //$display("Addr:%h, Data_in:%h, Data_out:%h", addr, data_in, data_out);
    end
endmodule

pd1/mem_test.vcd
$date
	Wed May 16 16:17:54 2018
$end
$version
	Icarus Verilog
$end
$timescale
	1s
$end
$scope module mem_test $end
$var reg 1 ! clock $end
$upscope $end
$scope module mem_test $end
$var reg 32 " addr [31:0] $end
$upscope $end
$scope module mem_test $end
$var reg 32 # data_in [31:0] $end
$upscope $end
$scope module mem_test $end
$var wire 32 $ data_out [31:0] $end
$upscope $end
$scope module mem_test $end
$var reg 1 % rw $end
$upscope $end
$scope module mem_test $end
$var reg 1 & enable $end
$upscope $end
$scope module mem_test $end
$var integer 32 ' counter [31:0] $end
$upscope $end
$scope module mem_test $end
$var reg 1 ( read_back $end
$upscope $end
$enddefinitions $end
#0
$dumpvars
0(
b0 '
1&
0%
bx $
bx #
b0 "
1!
$end
#5
0!
#10
b1 '
b100111101111011111111111101000 #
1!
#15
0!
#20
b100111101111011111111111101000 $
1!
#25
0!
#30
b10 '
b100100000000100000000000000011 #
bx $
b100 "
1!
#35
0!
#40
b100100000000100000000000000011 $
1!
#45
0!
#50
b11 '
b10101111101000100000000000001000 #
bx $
b1000 "
1!
#55
0!
#60
b10101111101000100000000000001000 $
1!
#65
0!
#70
b100 '
b100100000000100000000000000010 #
bx $
b1100 "
1!
#75
0!
#80
b100100000000100000000000000010 $
1!
#85
0!
#90
b101 '
b10101111101000100000000000001100 #
bx $
b10000 "
1!
#95
0!
#100
b10101111101000100000000000001100 $
1!
#105
0!
#110
b110 '
b10101111101000000000000000010000 #
bx $
b10100 "
1!
#115
0!
#120
b10101111101000000000000000010000 $
1!
#125
0!
#130
b111 '
b10001111101000110000000000001000 #
bx $
b11000 "
1!
#135
0!
#140
b10001111101000110000000000001000 $
1!
#145
0!
#150
b1000 '
b10001111101000100000000000001100 #
bx $
b11100 "
1!
#155
0!
#160
b10001111101000100000000000001100 $
1!
#165
0!
#170
b1001 '
b11000100001000000100001 #
bx $
b100000 "
1!
#175
0!
#180
b11000100001000000100001 $
1!
#185
0!
#190
b1010 '
b10101111101000100000000000010000 #
bx $
b100100 "
1!
#195
0!
#200
b10101111101000100000000000010000 $
1!
#205
0!
#210
b1011 '
b10001111101000100000000000010000 #
bx $
b101000 "
1!
#215
0!
#220
b10001111101000100000000000010000 $
1!
#225
0!
#230
b1100 '
b100111101111010000000000011000 #
bx $
b101100 "
1!
#235
0!
#240
b100111101111010000000000011000 $
1!
#245
0!
#250
b1101 '
b11111000000000000000001000 #
bx $
b110000 "
1!
#255
0!
#260
b11111000000000000000001000 $
1!
#265
0!
#270
b1110 '
b0 #
bx $
b110100 "
1!
#275
0!
#280
b0 $
1!
#285
0!
#290
b1111 '
bx $
b111000 "
1!
#295
0!
#300
b0 $
1!
#305
0!
#310
b10000 '
bx $
b111100 "
1!
#315
0!
#320
b0 $
1!
#325
0!
#330
b10001 '
b10100000000000000000000000001100 #
bx $
b1000000 "
1!
#335
0!
#340
b10100000000000000000000000001100 $
1!
#345
0!
#350
b10010 '
b0 #
bx $
b1000100 "
1!
#355
0!
#360
b0 $
1!
#365
0!
#370
b10011 '
bx $
b1001000 "
1!
#375
0!
#380
b0 $
1!
#385
0!
#390
b10100 '
bx $
b1001100 "
1!
#395
0!
#400
b0 $
1!
#405
0!
#410
b10101 '
bx $
b1010000 "
1!
#415
0!
#420
b0 $
1!
#425
0!
#430
b10110 '
bx $
b1010100 "
1!
#435
0!
#440
b0 $
1!
#445
0!
#450
b10111 '
b10000000000001 #
bx $
b1011000 "
1!
#455
0!
#460
b10000000000001 $
1!
#465
0!
#470
b11000 '
b1000000010000000000000001 #
bx $
b1011100 "
1!
#475
0!
#480
b1000000010000000000000001 $
1!
#485
0!
#490
b11001 '
b0 #
bx $
b1100000 "
1!
#495
0!
#500
b0 $
1!
#505
0!
#510
b11010 '
bx $
b1100100 "
1!
#515
0!
#520
b0 $
1!
#525
0!
#530
b11011 '
b1 #
bx $
b1101000 "
1!
#535
0!
#540
b1 $
1!
#545
0!
#550
b11100 '
b0 #
bx $
b1101100 "
1!
#555
0!
#560
1(
b100111101111011111111111101000 $
b0 "
b1 '
1%
1!
#565
0!
#570
b10 '
b100100000000100000000000000011 $
b100 "
1!
#575
0!
#580
b11 '
b10101111101000100000000000001000 $
b1000 "
1!
#585
0!
#590
b100 '
b100100000000100000000000000010 $
b1100 "
1!
#595
0!
#600
b101 '
b10101111101000100000000000001100 $
b10000 "
1!
#605
0!
#610
b110 '
b10101111101000000000000000010000 $
b10100 "
1!
#615
0!
#620
b111 '
b10001111101000110000000000001000 $
b11000 "
1!
#625
0!
#630
b1000 '
b10001111101000100000000000001100 $
b11100 "
1!
#635
0!
#640
b1001 '
b11000100001000000100001 $
b100000 "
1!
#645
0!
#650
b1010 '
b10101111101000100000000000010000 $
b100100 "
1!
#655
0!
#660
b1011 '
b10001111101000100000000000010000 $
b101000 "
1!
#665
0!
#670
b1100 '
b100111101111010000000000011000 $
b101100 "
1!
#675
0!
#680
b1101 '
b11111000000000000000001000 $
b110000 "
1!
#685
0!
#690
b1110 '
b0 $
b110100 "
1!
#695
0!
#700
b1111 '
b111000 "
1!
#705
0!
#710
b10000 '
b111100 "
1!
#715
0!
#720
b10001 '
b10100000000000000000000000001100 $
b1000000 "
1!
#725
0!
#730
b10010 '
b0 $
b1000100 "
1!
#735
0!
#740
b10011 '
b1001000 "
1!
#745
0!
#750
b10100 '
b1001100 "
1!
#755
0!
#760
b10101 '
b1010000 "
1!
#765
0!
#770
b10110 '
b1010100 "
1!
#775
0!
#780
b10111 '
b10000000000001 $
b1011000 "
1!
#785
0!
#790
b11000 '
b1000000010000000000000001 $
b1011100 "
1!
#795
0!
#800
b11001 '
b0 $
b1100000 "
1!
#805
0!
#810
b11010 '
b1100100 "
1!
#815
0!
#820
b11011 '
b1 $
b1101000 "
1!
#825
0!
#830
b11100 '
bx $
b1101100 "
1!
#835
0!
#840
b11101 '
b1110000 "
1!
#845
0!
#850
b11110 '
b1110100 "
1!
#855
0!
#860
b11111 '
b1111000 "
1!
#865
0!
#870
b100000 '
b1111100 "
1!
#875
0!
#880
b100001 '
b10000000 "
1!
#885
0!
#890
b100010 '
b10000100 "
1!
#895
0!
#900
b100011 '
b10001000 "
1!
#905
0!
#910
b100100 '
b10001100 "
1!
#915
0!
#920
b100101 '
b10010000 "
1!
#925
0!
#930
b100110 '
b10010100 "
1!
#935
0!
#940
b100111 '
b10011000 "
1!
#945
0!
#950
b101000 '
b10011100 "
1!
#955
0!
#960
b101001 '
b10100000 "
1!
#965
0!
#970
b101010 '
b10100100 "
1!
#975
0!
#980
b101011 '
b10101000 "
1!
#985
0!
#990
b101100 '
b10101100 "
1!
#995
0!
#1000
b101101 '
b10110000 "
1!
